dolvins/__init__.py
dolvins/dolvins.py
dolvins-0.0.6.dist-info/LICENSE.txt
dolvins-0.0.6.dist-info/METADATA
dolvins-0.0.6.dist-info/WHEEL
dolvins-0.0.6.dist-info/top_level.txt
dolvins-0.0.6.dist-info/RECORD
