Metadata-Version: 2.1
Name: dolvins
Version: 0.0.6
Summary: Dolvin's Math and Stats Library
Author: Landon Dolvin
Author-email: landondolvin@gmail.com
Keywords: python,distributions,probability,linear algebra,statistics,mathematics
Classifier: Development Status :: 4 - Beta
Classifier: Intended Audience :: Science/Research
Classifier: Programming Language :: Python :: 3
Classifier: Operating System :: Unix
Classifier: Operating System :: MacOS :: MacOS X
Classifier: Operating System :: Microsoft :: Windows
License-File: LICENSE.txt
Requires-Dist: psutil
Requires-Dist: numpy
Requires-Dist: pandas
Requires-Dist: tqdm
Requires-Dist: scipy
Requires-Dist: mpmath
